examples/alu8/src/alu8.v
// 8-bit ALU with flags
// Operations:
//   3'b000: ADD  (a + b)
//   3'b001: SUB  (a - b)
//   3'b010: AND  (a & b)
//   3'b011: OR   (a | b)
//   3'b100: XOR  (a ^ b)
//   3'b101: SHL  (a << 1)
//   3'b110: SHR  (a >> 1)
//   3'b111: NOT  (~a)
// Flags: zero (result == 0), negative (result[7]), carry (ADD/SUB only)

module alu8 (
    input  wire        clk,
    input  wire        rst_n,
    input  wire [7:0]  a,
    input  wire [7:0]  b,
    input  wire [2:0]  op,
    output reg  [7:0]  result,
    output reg         zero,
    output reg         negative,
    output reg         carry
);

    reg [8:0] tmp;  // 9-bit for carry detection

    always @(posedge clk or negedge rst_n) begin
        if (!rst_n) begin
            result   <= 8'h00;
            zero     <= 1'b0;
            negative <= 1'b0;
            carry    <= 1'b0;
        end else begin
            carry <= 1'b0;
            case (op)
                3'b000: begin
                    tmp     = {1'b0, a} + {1'b0, b};
                    result <= tmp[7:0];
                    carry  <= tmp[8];
                end
                3'b001: begin
                    tmp     = {1'b0, a} - {1'b0, b};
                    result <= tmp[7:0];
                    carry  <= tmp[8];   // borrow
                end
                3'b010: result <= a & b;
                3'b011: result <= a | b;
                3'b100: result <= a ^ b;
                3'b101: result <= a << 1;
                3'b110: result <= a >> 1;
                3'b111: result <= ~a;
            endcase

            zero     <= (result == 8'h00);
            negative <= result[7];
        end
    end

endmodule

examples/alu8/tb/tb_alu8.v
// Testbench for alu8
`timescale 1ns/1ps

module tb_alu8;

    reg        clk = 0;
    reg        rst_n = 0;
    reg  [7:0] a = 0;
    reg  [7:0] b = 0;
    reg  [2:0] op = 0;
    wire [7:0] result;
    wire       zero, negative, carry;

    integer pass_count = 0;
    integer fail_count = 0;

    alu8 uut (
        .clk(clk), .rst_n(rst_n),
        .a(a), .b(b), .op(op),
        .result(result), .zero(zero), .negative(negative), .carry(carry)
    );

    always #5 clk = ~clk;  // 100 MHz

    task apply_and_check;
        input [7:0] ta, tb_in;
        input [2:0] top;
        input [7:0] expected;
        input       expect_carry;
        input [127:0] label;
        begin
            @(negedge clk);
            a = ta; b = tb_in; op = top;
            @(posedge clk); #1;  // wait one clock + small delta
            @(posedge clk); #1;  // wait flag update
            if (result === expected && (top > 3'b001 || carry === expect_carry)) begin
                $display("PASS: %s  a=%h b=%h op=%b -> result=%h carry=%b zero=%b neg=%b",
                         label, ta, tb_in, top, result, carry, zero, negative);
                pass_count = pass_count + 1;
            end else begin
                $display("FAIL: %s  a=%h b=%h op=%b -> result=%h (expected %h) carry=%b",
                         label, ta, tb_in, top, result, expected, carry);
                fail_count = fail_count + 1;
            end
        end
    endtask

    initial begin
        $display("=== ALU8 Testbench Start ===");
        rst_n = 0;
        repeat(2) @(posedge clk);
        rst_n = 1;
        @(posedge clk);

        apply_and_check(8'h0A, 8'h05, 3'b000, 8'h0F, 1'b0, "ADD basic");
        apply_and_check(8'hFF, 8'h01, 3'b000, 8'h00, 1'b1, "ADD overflow");
        apply_and_check(8'h10, 8'h03, 3'b001, 8'h0D, 1'b0, "SUB basic");
        apply_and_check(8'h00, 8'h01, 3'b001, 8'hFF, 1'b1, "SUB borrow");
        apply_and_check(8'hF0, 8'h0F, 3'b010, 8'h00, 1'b0, "AND  ");
        apply_and_check(8'hF0, 8'h0F, 3'b011, 8'hFF, 1'b0, "OR   ");
        apply_and_check(8'hAA, 8'h55, 3'b100, 8'hFF, 1'b0, "XOR  ");
        apply_and_check(8'h81, 8'h00, 3'b101, 8'h02, 1'b0, "SHL  ");
        apply_and_check(8'h81, 8'h00, 3'b110, 8'h40, 1'b0, "SHR  ");
        apply_and_check(8'h0F, 8'h00, 3'b111, 8'hF0, 1'b0, "NOT  ");

        $display("=== Summary: %0d PASS, %0d FAIL ===", pass_count, fail_count);
        if (fail_count == 0)
            $display("PASS: All %0d tests passed!", pass_count);
        else
            $display("FAIL: %0d tests failed", fail_count);

        $finish;
    end

    initial begin
        #1000;
        $display("FAIL: Timeout");
        $finish;
    end

endmodule

examples/alu8/outputs/dump.vcd
$date
   Thu May 14 21:45:41 2026
$end
$version
  2017.4
$end
$timescale
  1ps
$end
$scope module tb_alu8 $end
$var reg 1 1 clk $end
$var reg 1 2 rst_n $end
$var reg 8 3 a [7:0] $end
$var reg 8 4 b [7:0] $end
$var reg 3 5 op [2:0] $end
$var wire 8 6 result [7:0] $end
$var wire 1 7 zero $end
$var wire 1 8 negative $end
$var wire 1 9 carry $end
$var integer 32 : pass_count $end
$var integer 32 ; fail_count $end
$scope module uut $end
$var wire 1 ! clk $end
$var wire 1 " rst_n $end
$var wire 8 # a [7:0] $end
$var wire 8 $ b [7:0] $end
$var wire 3 % op [2:0] $end
$var reg 8 & result [7:0] $end
$var reg 1 ' zero $end
$var reg 1 ( negative $end
$var reg 1 ) carry $end
$var reg 9 * tmp [8:0] $end
$upscope $end
$scope task apply_and_check $end
$var reg 8 + ta [7:0] $end
$var reg 8 , tb_in [7:0] $end
$var reg 3 - top [2:0] $end
$var reg 8 . expected [7:0] $end
$var reg 1 / expect_carry $end
$var reg 128 0 label [127:0] $end
$upscope $end
$upscope $end
$enddefinitions $end
#0
$dumpvars
0!
0"
b0 #
b0 $
b0 %
b0 &
0'
0(
0)
bx *
bx +
bx ,
bx -
bx .
x/
bx 0
01
02
b0 3
b0 4
b0 5
b0 6
07
08
09
b0 :
b0 ;
$end
#5000
1!
b0 &
0'
0(
0)
11
#10000
0!
01
#15000
1!
1"
b0 &
1'
0(
0)
b0 *
11
12
17
#20000
0!
01
#25000
1!
b0 &
1'
0(
0)
b1010 +
b101 ,
b0 -
b1111 .
0/
b10000010100010001000100001000000110001001100001011100110110100101100011 0
11
#30000
0!
b1010 #
b101 $
01
b1010 3
b101 4
b0 5
#35000
1!
b1111 &
1'
0(
0)
b1111 *
11
b1111 6
#40000
0!
01
#45000
1!
b1111 &
0'
0(
0)
11
07
#46000
b11111111 +
b1 ,
b0 .
1/
b10000010100010001000100001000000110111101110110011001010111001001100110011011000110111101110111 0
b1 :
#50000
0!
b11111111 #
b1 $
01
b11111111 3
b1 4
b0 5
#55000
1!
b0 &
0'
0(
1)
b100000000 *
11
b0 6
19
#60000
0!
01
#65000
1!
b0 &
1'
0(
1)
11
17
#66000
b10000 +
b11 ,
b1 -
b1101 .
0/
b10100110101010101000010001000000110001001100001011100110110100101100011 0
b10 :
#70000
0!
b10000 #
b11 $
b1 %
01
b10000 3
b11 4
b1 5
#75000
1!
b1101 &
1'
0(
0)
b1101 *
11
b1101 6
09
#80000
0!
01
#85000
1!
b1101 &
0'
0(
0)
11
07
#86000
b0 +
b1 ,
b11111111 .
1/
b1010011010101010100001000100000011000100110111101110010011100100110111101110111 0
b11 :
#90000
0!
b0 #
b1 $
01
b0 3
b1 4
b1 5
#95000
1!
b11111111 &
0'
0(
1)
b111111111 *
11
b11111111 6
19
#100000
0!
01
#105000
1!
b11111111 &
0'
1(
1)
11
18
#106000
b11110000 +
b1111 ,
b10 -
b0 .
0/
b100000101001110010001000010000000100000 0
b100 :
#110000
0!
b11110000 #
b1111 $
b10 %
01
b11110000 3
b1111 4
b10 5
#115000
1!
b0 &
0'
1(
0)
11
b0 6
09
#120000
0!
01
#125000
1!
b0 &
1'
0(
0)
11
17
08
#126000
b11 -
b11111111 .
b100111101010010001000000010000000100000 0
b101 :
#130000
0!
b11 %
01
b11110000 3
b1111 4
b11 5
#135000
1!
b11111111 &
1'
0(
0)
11
b11111111 6
#140000
0!
01
#145000
1!
b11111111 &
0'
1(
0)
11
07
18
#146000
b10101010 +
b1010101 ,
b100 -
b101100001001111010100100010000000100000 0
b110 :
#150000
0!
b10101010 #
b1010101 $
b100 %
01
b10101010 3
b1010101 4
b100 5
#155000
1!
b11111111 &
0'
1(
0)
11
#160000
0!
01
#165000
1!
b11111111 &
0'
1(
0)
11
#166000
b10000001 +
b0 ,
b101 -
b10 .
b101001101001000010011000010000000100000 0
b111 :
#170000
0!
b10000001 #
b0 $
b101 %
01
b10000001 3
b0 4
b101 5
#175000
1!
b10 &
0'
1(
0)
11
b10 6
#180000
0!
01
#185000
1!
b10 &
0'
0(
0)
11
08
#186000
b110 -
b1000000 .
b101001101001000010100100010000000100000 0
b1000 :
#190000
0!
b110 %
01
b10000001 3
b0 4
b110 5
#195000
1!
b1000000 &
0'
0(
0)
11
b1000000 6
#200000
0!
01
#205000
1!
b1000000 &
0'
0(
0)
11
#206000
b1111 +
b111 -
b11110000 .
b100111001001111010101000010000000100000 0
b1001 :
#210000
0!
b1111 #
b111 %
01
b1111 3
b0 4
b111 5
#215000
1!
b11110000 &
0'
0(
0)
11
b11110000 6
#220000
0!
01
#225000
1!
b11110000 &
0'
1(
0)
11
18
#226000
b1010 :
